asent/__init__.py
asent/about.py
asent/component.py
asent/constants.py
asent/data_classes.py
asent/getters.py
asent/utils.py
asent/visualize.py
asent/lang/__init__.py
asent/lang/da.py
asent/lang/emoji.py
asent/lang/en.py
asent/lang/no.py
asent/lang/sv.py
asent/lang/xx.py
asent/lexicons/af_lexicon_chen_skiena_2014_v1.txt
asent/lexicons/an_lexicon_chen_skiena_2014_v1.txt
asent/lexicons/ar_lexicon_chen_skiena_2014_v1.txt
asent/lexicons/az_lexicon_chen_skiena_2014_v1.txt
asent/lexicons/be_lexicon_chen_skiena_2014_v1.txt
asent/lexicons/bg_lexicon_chen_skiena_2014_v1.txt
asent/lexicons/bn_lexicon_chen_skiena_2014_v1.txt
asent/lexicons/br_lexicon_chen_skiena_2014_v1.txt
asent/lexicons/bs_lexicon_chen_skiena_2014_v1.txt
asent/lexicons/ca_lexicon_chen_skiena_2014_v1.txt
asent/lexicons/cs_lexicon_chen_skiena_2014_v1.txt
asent/lexicons/cy_lexicon_chen_skiena_2014_v1.txt
asent/lexicons/da_lexicon_afinn_v1.txt
asent/lexicons/da_lexicon_chen_skiena_2014_v1.txt
asent/lexicons/da_lexicon_sentida_lemma_v1.csv
asent/lexicons/de_lexicon_chen_skiena_2014_v1.txt
asent/lexicons/el_lexicon_chen_skiena_2014_v1.txt
asent/lexicons/emoji_v1.json
asent/lexicons/en_lexicon_v1.txt
asent/lexicons/eo_lexicon_chen_skiena_2014_v1.txt
asent/lexicons/es_lexicon_chen_skiena_2014_v1.txt
asent/lexicons/et_lexicon_chen_skiena_2014_v1.txt
asent/lexicons/eu_lexicon_chen_skiena_2014_v1.txt
asent/lexicons/fa_lexicon_chen_skiena_2014_v1.txt
asent/lexicons/fi_lexicon_chen_skiena_2014_v1.txt
asent/lexicons/fo_lexicon_chen_skiena_2014_v1.txt
asent/lexicons/fr_lexicon_chen_skiena_2014_v1.txt
asent/lexicons/fy_lexicon_chen_skiena_2014_v1.txt
asent/lexicons/ga_lexicon_chen_skiena_2014_v1.txt
asent/lexicons/gd_lexicon_chen_skiena_2014_v1.txt
asent/lexicons/gl_lexicon_chen_skiena_2014_v1.txt
asent/lexicons/gu_lexicon_chen_skiena_2014_v1.txt
asent/lexicons/he_lexicon_chen_skiena_2014_v1.txt
asent/lexicons/hi_lexicon_chen_skiena_2014_v1.txt
asent/lexicons/hr_lexicon_chen_skiena_2014_v1.txt
asent-0.8.3.dist-info/LICENSE
asent-0.8.3.dist-info/METADATA
asent-0.8.3.dist-info/WHEEL
asent-0.8.3.dist-info/top_level.txt
asent-0.8.3.dist-info/RECORD
