Metadata-Version: 2.1
Name: asent
Version: 0.8.3
Summary: A python package for flexible and transparent sentiment analysis.
Author-email: Kenneth Enevoldsen <kennethcenevoldsen@gmail.com>
License: MIT License
Project-URL: Homepage, https://github.com/KennethEnevoldsen/asent
Project-URL: repository, https://github.com/KennethEnevoldsen/asent
Project-URL: documentation, https://kennethenevoldsen.github.io/asent/
Keywords: nlp,sentiment analysis,spacy,spaCy,spaCy 3,text analysis,aspect-based sentiment analysis,ABSA
Classifier: Development Status :: 5 - Production/Stable
Classifier: Environment :: Console
Classifier: Intended Audience :: Developers
Classifier: Intended Audience :: Science/Research
Classifier: Topic :: Scientific/Engineering
Classifier: Topic :: Scientific/Engineering :: Artificial Intelligence
Classifier: License :: OSI Approved :: MIT License
Classifier: Operating System :: POSIX :: Linux
Classifier: Operating System :: MacOS :: MacOS X
Classifier: Operating System :: Microsoft :: Windows
Classifier: Programming Language :: Python :: 3
Classifier: Programming Language :: Python :: 3.8
Classifier: Programming Language :: Python :: 3.9
Requires-Python: >=3.9
License-File: LICENSE
Requires-Dist: spacy >=3.0.0
Requires-Dist: matplotlib >=3.5.0
Provides-Extra: all
Requires-Dist: nltk >=3.6.7 ; extra == 'all'
Provides-Extra: da
Requires-Dist: dacy >=1.1.0 ; extra == 'da'
Provides-Extra: docs
Requires-Dist: sphinx ==5.3.0 ; extra == 'docs'
Requires-Dist: furo ==2022.12.7 ; extra == 'docs'
Requires-Dist: sphinx-copybutton >=0.5.1 ; extra == 'docs'
Requires-Dist: sphinxext-opengraph >=0.7.3 ; extra == 'docs'
Requires-Dist: sphinx-design >=0.3.0 ; extra == 'docs'
Requires-Dist: myst-nb >=0.6.0 ; extra == 'docs'
Requires-Dist: black >=22.12.0 ; extra == 'docs'
Requires-Dist: pre-commit >=2.20.0 ; extra == 'docs'
Requires-Dist: ruff >=0.0.263 ; extra == 'docs'
Requires-Dist: pyright ==1.1.325 ; extra == 'docs'
Requires-Dist: jupyter >=1.0.0 ; extra == 'docs'
Provides-Extra: tests
Requires-Dist: pytest >=7.1.3 ; extra == 'tests'
Requires-Dist: pytest-cov >=3.0.0 ; extra == 'tests'
